{
  "Index": 626,
  "Name": "GoldPatternBoots",
  "Type": 10,
  "Grade": 2,
  "RequiredType": 0,
  "RequiredClass": 31,
  "RequiredGender": 3,
  "Set": 0,
  "Shape": 0,
  "Weight": 2,
  "Light": 0,
  "RequiredAmount": 50,
  "Image": 857,
  "Durability": 15000,
  "Price": 150000,
  "StackSize": 1,
  "StartItem": false,
  "Effect": 0,
  "NeedIdentify": false,
  "ShowGroupPickup": true,
  "GlobalDropNotify": false,
  "ClassBased": false,
  "LevelBased": false,
  "CanMine": false,
  "CanFastRun": false,
  "CanAwakening": false,
  "Bind": 0,
  "Unique": 0,
  "RandomStatsId": 8,
  "RandomStats": null,
  "ToolTip": "",
  "Slots": 0,
  "Stats": {
    "Values": {
      "MaxAC": 1,
      "MaxMAC": 1,
      "MaxDC": 1,
      "MaxMC": 1,
      "MaxSC": 1
    },
    "Count": 5
  },
  "IsConsumable": false,
  "IsFishingRod": false,
  "FriendlyName": "GoldPatternBoots"
}