{
  "Index": 375,
  "Name": "MinotaurKing",
  "Image": 101,
  "AI": 33,
  "Effect": 0,
  "ViewRange": 7,
  "CoolEye": 0,
  "Level": 60,
  "Light": 10,
  "AttackSpeed": 1000,
  "MoveSpeed": 300,
  "Experience": 15000,
  "DropPath": "",
  "Drops": [
    {
      "Chance": 60,
      "Gold": 0,
      "GroupedDrop": null,
      "Type": 0,
      "QuestRequired": false,
      "ItemName": "GoldBar"
    },
    {
      "Chance": 45,
      "Gold": 0,
      "GroupedDrop": null,
      "Type": 0,
      "QuestRequired": false,
      "ItemName": "SoulSpringWand"
    },
    {
      "Chance": 500,
      "Gold": 0,
      "GroupedDrop": null,
      "Type": 0,
      "QuestRequired": false,
      "ItemName": "BladesOfMagi"
    },
    {
      "Chance": 500,
      "Gold": 0,
      "GroupedDrop": null,
      "Type": 0,
      "QuestRequired": false,
      "ItemName": "HeavenSword"
    },
    {
      "Chance": 500,
      "Gold": 0,
      "GroupedDrop": null,
      "Type": 0,
      "QuestRequired": false,
      "ItemName": "BladeOfSorcery"
    },
    {
      "Chance": 500,
      "Gold": 0,
      "GroupedDrop": null,
      "Type": 0,
      "QuestRequired": false,
      "ItemName": "SwordOfWarGod"
    },
    {
      "Chance": 200,
      "Gold": 0,
      "GroupedDrop": null,
      "Type": 0,
      "QuestRequired": false,
      "ItemName": "MaleficBow"
    },
    {
      "Chance": 200,
      "Gold": 0,
      "GroupedDrop": null,
      "Type": 0,
      "QuestRequired": false,
      "ItemName": "RoyalBlades"
    },
    {
      "Chance": 200,
      "Gold": 0,
      "GroupedDrop": null,
      "Type": 0,
      "QuestRequired": false,
      "ItemName": "SoulSabre"
    },
    {
      "Chance": 200,
      "Gold": 0,
      "GroupedDrop": null,
      "Type": 0,
      "QuestRequired": false,
      "ItemName": "DragonStaff"
    },
    {
      "Chance": 200,
      "Gold": 0,
      "GroupedDrop": null,
      "Type": 0,
      "QuestRequired": false,
      "ItemName": "DragonSlayer"
    },
    {
      "Chance": 125,
      "Gold": 0,
      "GroupedDrop": null,
      "Type": 0,
      "QuestRequired": false,
      "ItemName": "LitheBow"
    },
    {
      "Chance": 125,
      "Gold": 0,
      "GroupedDrop": null,
      "Type": 0,
      "QuestRequired": false,
      "ItemName": "FreezingBlades"
    },
    {
      "Chance": 125,
      "Gold": 0,
      "GroupedDrop": null,
      "Type": 0,
      "QuestRequired": false,
      "ItemName": "StoneBambooFan"
    },
    {
      "Chance": 125,
      "Gold": 0,
      "GroupedDrop": null,
      "Type": 0,
      "QuestRequired": false,
      "ItemName": "MagicScythe"
    },
    {
      "Chance": 125,
      "Gold": 0,
      "GroupedDrop": null,
      "Type": 0,
      "QuestRequired": false,
      "ItemName": "WarSpiritBlade"
    },
    {
      "Chance": 45,
      "Gold": 0,
      "GroupedDrop": null,
      "Type": 0,
      "QuestRequired": false,
      "ItemName": "FiendBow"
    },
    {
      "Chance": 45,
      "Gold": 0,
      "GroupedDrop": null,
      "Type": 0,
      "QuestRequired": false,
      "ItemName": "BladesOfDarkness"
    },
    {
      "Chance": 45,
      "Gold": 0,
      "GroupedDrop": null,
      "Type": 0,
      "QuestRequired": false,
      "ItemName": "JudgementMace"
    },
    {
      "Chance": 500,
      "Gold": 0,
      "GroupedDrop": null,
      "Type": 0,
      "QuestRequired": false,
      "ItemName": "BowOfForce"
    },
    {
      "Chance": 45,
      "Gold": 0,
      "GroupedDrop": null,
      "Type": 0,
      "QuestRequired": false,
      "ItemName": "WarMageStaff"
    },
    {
      "Chance": 25,
      "Gold": 0,
      "GroupedDrop": null,
      "Type": 0,
      "QuestRequired": false,
      "ItemName": "SteelArmour(F)"
    },
    {
      "Chance": 25,
      "Gold": 0,
      "GroupedDrop": null,
      "Type": 0,
      "QuestRequired": false,
      "ItemName": "DragonRobe(M)"
    },
    {
      "Chance": 350,
      "Gold": 0,
      "GroupedDrop": null,
      "Type": 0,
      "QuestRequired": false,
      "ItemName": "LightTemperedArmour(M)"
    },
    {
      "Chance": 350,
      "Gold": 0,
      "GroupedDrop": null,
      "Type": 0,
      "QuestRequired": false,
      "ItemName": "StealthArmour(F)"
    },
    {
      "Chance": 350,
      "Gold": 0,
      "GroupedDrop": null,
      "Type": 0,
      "QuestRequired": false,
      "ItemName": "StealthArmour(M)"
    },
    {
      "Chance": 350,
      "Gold": 0,
      "GroupedDrop": null,
      "Type": 0,
      "QuestRequired": false,
      "ItemName": "CraneArmour(F)"
    },
    {
      "Chance": 350,
      "Gold": 0,
      "GroupedDrop": null,
      "Type": 0,
      "QuestRequired": false,
      "ItemName": "CraneArmour(M)"
    },
    {
      "Chance": 350,
      "Gold": 0,
      "GroupedDrop": null,
      "Type": 0,
      "QuestRequired": false,
      "ItemName": "LotusArmour(F)"
    },
    {
      "Chance": 350,
      "Gold": 0,
      "GroupedDrop": null,
      "Type": 0,
      "QuestRequired": false,
      "ItemName": "LotusArmour(M)"
    },
    {
      "Chance": 350,
      "Gold": 0,
      "GroupedDrop": null,
      "Type": 0,
      "QuestRequired": false,
      "ItemName": "BlackTigerArmour(F)"
    },
    {
      "Chance": 500,
      "Gold": 0,
      "GroupedDrop": null,
      "Type": 0,
      "QuestRequired": false,
      "ItemName": "HeavenArmour(F)"
    },
    {
      "Chance": 500,
      "Gold": 0,
      "GroupedDrop": null,
      "Type": 0,
      "QuestRequired": false,
      "ItemName": "HeavenArmour(M)"
    },
    {
      "Chance": 25,
      "Gold": 0,
      "GroupedDrop": null,
      "Type": 0,
      "QuestRequired": false,
      "ItemName": "StuddedArmour(F)"
    },
    {
      "Chance": 25,
      "Gold": 0,
      "GroupedDrop": null,
      "Type": 0,
      "QuestRequired": false,
      "ItemName": "StuddedArmour(M)"
    },
    {
      "Chance": 25,
      "Gold": 0,
      "GroupedDrop": null,
      "Type": 0,
      "QuestRequired": false,
      "ItemName": "RoyalArmour(F)"
    },
    {
      "Chance": 25,
      "Gold": 0,
      "GroupedDrop": null,
      "Type": 0,
      "QuestRequired": false,
      "ItemName": "RoyalArmour(M)"
    },
    {
      "Chance": 25,
      "Gold": 0,
      "GroupedDrop": null,
      "Type": 0,
      "QuestRequired": false,
      "ItemName": "TitanArmour(F)"
    },
    {
      "Chance": 25,
      "Gold": 0,
      "GroupedDrop": null,
      "Type": 0,
      "QuestRequired": false,
      "ItemName": "TitanArmour(M)"
    },
    {
      "Chance": 25,
      "Gold": 0,
      "GroupedDrop": null,
      "Type": 0,
      "QuestRequired": false,
      "ItemName": "DragonRobe(F)"
    },
    {
      "Chance": 25,
      "Gold": 0,
      "GroupedDrop": null,
      "Type": 0,
      "QuestRequired": false,
      "ItemName": "SteelArmour(M)"
    },
    {
      "Chance": 350,
      "Gold": 0,
      "GroupedDrop": null,
      "Type": 0,
      "QuestRequired": false,
      "ItemName": "LightTemperedArmour(F)"
    },
    {
      "Chance": 350,
      "Gold": 0,
      "GroupedDrop": null,
      "Type": 0,
      "QuestRequired": false,
      "ItemName": "BlackTigerArmour(M)"
    },
    {
      "Chance": 5,
      "Gold": 0,
      "GroupedDrop": null,
      "Type": 0,
      "QuestRequired": false,
      "ItemName": "SkeletonHelmet"
    },
    {
      "Chance": 70,
      "Gold": 0,
      "GroupedDrop": null,
      "Type": 0,
      "QuestRequired": false,
      "ItemName": "BlackIronHelmet"
    },
    {
      "Chance": 90,
      "Gold": 0,
      "GroupedDrop": null,
      "Type": 0,
      "QuestRequired": false,
      "ItemName": "HelmetOfHero"
    },
    {
      "Chance": 150,
      "Gold": 0,
      "GroupedDrop": null,
      "Type": 0,
      "QuestRequired": false,
      "ItemName": "GreatHelmet"
    },
    {
      "Chance": 150,
      "Gold": 0,
      "GroupedDrop": null,
      "Type": 0,
      "QuestRequired": false,
      "ItemName": "WisdomCoronet"
    },
    {
      "Chance": 150,
      "Gold": 0,
      "GroupedDrop": null,
      "Type": 0,
      "QuestRequired": false,
      "ItemName": "TaoCoronet"
    },
    {
      "Chance": 150,
      "Gold": 0,
      "GroupedDrop": null,
      "Type": 0,
      "QuestRequired": false,
      "ItemName": "RoyalHelmet"
    },
    {
      "Chance": 10,
      "Gold": 0,
      "GroupedDrop": null,
      "Type": 0,
      "QuestRequired": false,
      "ItemName": "BrassHelmet"
    },
    {
      "Chance": 15,
      "Gold": 0,
      "GroupedDrop": null,
      "Type": 0,
      "QuestRequired": false,
      "ItemName": "SteelHelmet"
    },
    {
      "Chance": 5,
      "Gold": 0,
      "GroupedDrop": null,
      "Type": 0,
      "QuestRequired": false,
      "ItemName": "ShamanHelmet"
    },
    {
      "Chance": 80,
      "Gold": 0,
      "GroupedDrop": null,
      "Type": 0,
      "QuestRequired": false,
      "ItemName": "SoulNecklace"
    },
    {
      "Chance": 5,
      "Gold": 0,
      "GroupedDrop": null,
      "Type": 0,
      "QuestRequired": false,
      "ItemName": "TigerNecklace"
    },
    {
      "Chance": 5,
      "Gold": 0,
      "GroupedDrop": null,
      "Type": 0,
      "QuestRequired": false,
      "ItemName": "LanternNecklace"
    },
    {
      "Chance": 45,
      "Gold": 0,
      "GroupedDrop": null,
      "Type": 0,
      "QuestRequired": false,
      "ItemName": "PearlNecklace"
    },
    {
      "Chance": 45,
      "Gold": 0,
      "GroupedDrop": null,
      "Type": 0,
      "QuestRequired": false,
      "ItemName": "LifeNecklace"
    },
    {
      "Chance": 45,
      "Gold": 0,
      "GroupedDrop": null,
      "Type": 0,
      "QuestRequired": false,
      "ItemName": "ClawNecklace"
    },
    {
      "Chance": 80,
      "Gold": 0,
      "GroupedDrop": null,
      "Type": 0,
      "QuestRequired": false,
      "ItemName": "GreenBead"
    },
    {
      "Chance": 80,
      "Gold": 0,
      "GroupedDrop": null,
      "Type": 0,
      "QuestRequired": false,
      "ItemName": "DemonicBells"
    },
    {
      "Chance": 80,
      "Gold": 0,
      "GroupedDrop": null,
      "Type": 0,
      "QuestRequired": false,
      "ItemName": "GaleNecklace"
    },
    {
      "Chance": 250,
      "Gold": 0,
      "GroupedDrop": null,
      "Type": 0,
      "QuestRequired": false,
      "ItemName": "BaekTaGlove"
    },
    {
      "Chance": 250,
      "Gold": 0,
      "GroupedDrop": null,
      "Type": 0,
      "QuestRequired": false,
      "ItemName": "HolyTaoWheel"
    },
    {
      "Chance": 250,
      "Gold": 0,
      "GroupedDrop": null,
      "Type": 0,
      "QuestRequired": false,
      "ItemName": "SpiritReformer"
    },
    {
      "Chance": 100,
      "Gold": 0,
      "GroupedDrop": null,
      "Type": 0,
      "QuestRequired": false,
      "ItemName": "8TrigramWheel"
    },
    {
      "Chance": 100,
      "Gold": 0,
      "GroupedDrop": null,
      "Type": 0,
      "QuestRequired": false,
      "ItemName": "HangMaWheel"
    },
    {
      "Chance": 100,
      "Gold": 0,
      "GroupedDrop": null,
      "Type": 0,
      "QuestRequired": false,
      "ItemName": "BokMaWheel"
    },
    {
      "Chance": 30,
      "Gold": 0,
      "GroupedDrop": null,
      "Type": 0,
      "QuestRequired": false,
      "ItemName": "SpellBracelet"
    },
    {
      "Chance": 55,
      "Gold": 0,
      "GroupedDrop": null,
      "Type": 0,
      "QuestRequired": false,
      "ItemName": "SteelGlove"
    },
    {
      "Chance": 75,
      "Gold": 0,
      "GroupedDrop": null,
      "Type": 0,
      "QuestRequired": false,
      "ItemName": "SoulSpringBracelet"
    },
    {
      "Chance": 75,
      "Gold": 0,
      "GroupedDrop": null,
      "Type": 0,
      "QuestRequired": false,
      "ItemName": "DragonBracelet"
    },
    {
      "Chance": 75,
      "Gold": 0,
      "GroupedDrop": null,
      "Type": 0,
      "QuestRequired": false,
      "ItemName": "KnightBracelet"
    },
    {
      "Chance": 30,
      "Gold": 0,
      "GroupedDrop": null,
      "Type": 0,
      "QuestRequired": false,
      "ItemName": "3rdEyeBracelet"
    },
    {
      "Chance": 25,
      "Gold": 0,
      "GroupedDrop": null,
      "Type": 0,
      "QuestRequired": false,
      "ItemName": "DragonRing"
    },
    {
      "Chance": 25,
      "Gold": 0,
      "GroupedDrop": null,
      "Type": 0,
      "QuestRequired": false,
      "ItemName": "RubyRing"
    },
    {
      "Chance": 25,
      "Gold": 0,
      "GroupedDrop": null,
      "Type": 0,
      "QuestRequired": false,
      "ItemName": "PlatinumRing"
    },
    {
      "Chance": 50,
      "Gold": 0,
      "GroupedDrop": null,
      "Type": 0,
      "QuestRequired": false,
      "ItemName": "PowerRing"
    },
    {
      "Chance": 100,
      "Gold": 0,
      "GroupedDrop": null,
      "Type": 0,
      "QuestRequired": false,
      "ItemName": "NobleRing"
    },
    {
      "Chance": 50,
      "Gold": 0,
      "GroupedDrop": null,
      "Type": 0,
      "QuestRequired": false,
      "ItemName": "TitanRing"
    },
    {
      "Chance": 2000,
      "Gold": 0,
      "GroupedDrop": null,
      "Type": 0,
      "QuestRequired": false,
      "ItemName": "ClearRing"
    },
    {
      "Chance": 1000,
      "Gold": 0,
      "GroupedDrop": null,
      "Type": 0,
      "QuestRequired": false,
      "ItemName": "HardenedRing"
    },
    {
      "Chance": 50,
      "Gold": 0,
      "GroupedDrop": null,
      "Type": 0,
      "QuestRequired": false,
      "ItemName": "VioletRing"
    },
    {
      "Chance": 5000,
      "Gold": 0,
      "GroupedDrop": null,
      "Type": 0,
      "QuestRequired": false,
      "ItemName": "RevivalRing"
    },
    {
      "Chance": 500,
      "Gold": 0,
      "GroupedDrop": null,
      "Type": 0,
      "QuestRequired": false,
      "ItemName": "MuscleRing"
    },
    {
      "Chance": 500,
      "Gold": 0,
      "GroupedDrop": null,
      "Type": 0,
      "QuestRequired": false,
      "ItemName": "RecoveryRing"
    },
    {
      "Chance": 4000,
      "Gold": 0,
      "GroupedDrop": null,
      "Type": 0,
      "QuestRequired": false,
      "ItemName": "ParalysisRing"
    },
    {
      "Chance": 3500,
      "Gold": 0,
      "GroupedDrop": null,
      "Type": 0,
      "QuestRequired": false,
      "ItemName": "TeleportRing"
    },
    {
      "Chance": 10,
      "Gold": 0,
      "GroupedDrop": null,
      "Type": 0,
      "QuestRequired": false,
      "ItemName": "GaleRing"
    },
    {
      "Chance": 250,
      "Gold": 0,
      "GroupedDrop": null,
      "Type": 0,
      "QuestRequired": false,
      "ItemName": "TaeGukRing"
    },
    {
      "Chance": 250,
      "Gold": 0,
      "GroupedDrop": null,
      "Type": 0,
      "QuestRequired": false,
      "ItemName": "ThunderRing"
    },
    {
      "Chance": 250,
      "Gold": 0,
      "GroupedDrop": null,
      "Type": 0,
      "QuestRequired": false,
      "ItemName": "BoundlessRing"
    },
    {
      "Chance": 100,
      "Gold": 0,
      "GroupedDrop": null,
      "Type": 0,
      "QuestRequired": false,
      "ItemName": "SoulRing"
    },
    {
      "Chance": 100,
      "Gold": 0,
      "GroupedDrop": null,
      "Type": 0,
      "QuestRequired": false,
      "ItemName": "OmaSpiritRing"
    },
    {
      "Chance": 4000,
      "Gold": 0,
      "GroupedDrop": null,
      "Type": 0,
      "QuestRequired": false,
      "ItemName": "ProtectionRing"
    },
    {
      "Chance": 5,
      "Gold": 0,
      "GroupedDrop": null,
      "Type": 0,
      "QuestRequired": false,
      "ItemName": "AmuletOfRevival"
    },
    {
      "Chance": 60,
      "Gold": 0,
      "GroupedDrop": null,
      "Type": 0,
      "QuestRequired": false,
      "ItemName": "AdamantineBelt"
    },
    {
      "Chance": 30,
      "Gold": 0,
      "GroupedDrop": null,
      "Type": 0,
      "QuestRequired": false,
      "ItemName": "GoldBelt"
    },
    {
      "Chance": 30,
      "Gold": 0,
      "GroupedDrop": null,
      "Type": 0,
      "QuestRequired": false,
      "ItemName": "BronzeBelt"
    },
    {
      "Chance": 20,
      "Gold": 0,
      "GroupedDrop": null,
      "Type": 0,
      "QuestRequired": false,
      "ItemName": "ChainBelt"
    },
    {
      "Chance": 30,
      "Gold": 0,
      "GroupedDrop": null,
      "Type": 0,
      "QuestRequired": false,
      "ItemName": "DragonBoots"
    },
    {
      "Chance": 30,
      "Gold": 0,
      "GroupedDrop": null,
      "Type": 0,
      "QuestRequired": false,
      "ItemName": "RedScaleBoots"
    },
    {
      "Chance": 15,
      "Gold": 0,
      "GroupedDrop": null,
      "Type": 0,
      "QuestRequired": false,
      "ItemName": "SilkBoots"
    },
    {
      "Chance": 20,
      "Gold": 0,
      "GroupedDrop": null,
      "Type": 0,
      "QuestRequired": false,
      "ItemName": "BlackBoots"
    },
    {
      "Chance": 100,
      "Gold": 0,
      "GroupedDrop": null,
      "Type": 0,
      "QuestRequired": false,
      "ItemName": "MCStone"
    },
    {
      "Chance": 100,
      "Gold": 0,
      "GroupedDrop": null,
      "Type": 0,
      "QuestRequired": false,
      "ItemName": "SCStone"
    },
    {
      "Chance": 100,
      "Gold": 0,
      "GroupedDrop": null,
      "Type": 0,
      "QuestRequired": false,
      "ItemName": "MagicStone"
    },
    {
      "Chance": 100,
      "Gold": 0,
      "GroupedDrop": null,
      "Type": 0,
      "QuestRequired": false,
      "ItemName": "DCStone"
    },
    {
      "Chance": 100,
      "Gold": 0,
      "GroupedDrop": null,
      "Type": 0,
      "QuestRequired": false,
      "ItemName": "HealthStone"
    },
    {
      "Chance": 30,
      "Gold": 0,
      "GroupedDrop": null,
      "Type": 0,
      "QuestRequired": false,
      "ItemName": "ImpactDrug(M)"
    },
    {
      "Chance": 2,
      "Gold": 0,
      "GroupedDrop": null,
      "Type": 0,
      "QuestRequired": false,
      "ItemName": "SunPotion(M)"
    },
    {
      "Chance": 30,
      "Gold": 0,
      "GroupedDrop": null,
      "Type": 0,
      "QuestRequired": false,
      "ItemName": "StormDrug(M)"
    },
    {
      "Chance": 2,
      "Gold": 0,
      "GroupedDrop": null,
      "Type": 0,
      "QuestRequired": false,
      "ItemName": "SunPotion(M)"
    },
    {
      "Chance": 2,
      "Gold": 0,
      "GroupedDrop": null,
      "Type": 0,
      "QuestRequired": false,
      "ItemName": "SunPotion(M)"
    },
    {
      "Chance": 2,
      "Gold": 0,
      "GroupedDrop": null,
      "Type": 0,
      "QuestRequired": false,
      "ItemName": "SunPotion(M)"
    },
    {
      "Chance": 1,
      "Gold": 0,
      "GroupedDrop": null,
      "Type": 0,
      "QuestRequired": false,
      "ItemName": "(HP)DrugXL"
    },
    {
      "Chance": 1,
      "Gold": 0,
      "GroupedDrop": null,
      "Type": 0,
      "QuestRequired": false,
      "ItemName": "(HP)DrugXL"
    },
    {
      "Chance": 2,
      "Gold": 0,
      "GroupedDrop": null,
      "Type": 0,
      "QuestRequired": false,
      "ItemName": "SunPotion(M)"
    },
    {
      "Chance": 2,
      "Gold": 0,
      "GroupedDrop": null,
      "Type": 0,
      "QuestRequired": false,
      "ItemName": "(HP)DrugXL"
    },
    {
      "Chance": 1,
      "Gold": 0,
      "GroupedDrop": null,
      "Type": 0,
      "QuestRequired": false,
      "ItemName": "(MP)DrugXL"
    },
    {
      "Chance": 1,
      "Gold": 0,
      "GroupedDrop": null,
      "Type": 0,
      "QuestRequired": false,
      "ItemName": "(MP)DrugXL"
    },
    {
      "Chance": 2,
      "Gold": 0,
      "GroupedDrop": null,
      "Type": 0,
      "QuestRequired": false,
      "ItemName": "(MP)DrugXL"
    },
    {
      "Chance": 2,
      "Gold": 0,
      "GroupedDrop": null,
      "Type": 0,
      "QuestRequired": false,
      "ItemName": "(MP)DrugXL"
    },
    {
      "Chance": 30,
      "Gold": 0,
      "GroupedDrop": null,
      "Type": 0,
      "QuestRequired": false,
      "ItemName": "TaoistDrug(M)"
    },
    {
      "Chance": 30,
      "Gold": 0,
      "GroupedDrop": null,
      "Type": 0,
      "QuestRequired": false,
      "ItemName": "MagicDrug(M)"
    },
    {
      "Chance": 2,
      "Gold": 0,
      "GroupedDrop": null,
      "Type": 0,
      "QuestRequired": false,
      "ItemName": "(HP)DrugXL"
    },
    {
      "Chance": 2,
      "Gold": 0,
      "GroupedDrop": null,
      "Type": 0,
      "QuestRequired": false,
      "ItemName": "SunPotion(M)"
    },
    {
      "Chance": 1,
      "Gold": 0,
      "GroupedDrop": null,
      "Type": 0,
      "QuestRequired": false,
      "ItemName": "SunPotion(M)"
    },
    {
      "Chance": 2,
      "Gold": 0,
      "GroupedDrop": null,
      "Type": 0,
      "QuestRequired": false,
      "ItemName": "(HP)DrugLarge"
    },
    {
      "Chance": 1,
      "Gold": 0,
      "GroupedDrop": null,
      "Type": 0,
      "QuestRequired": false,
      "ItemName": "(HP)DrugLarge"
    },
    {
      "Chance": 1,
      "Gold": 0,
      "GroupedDrop": null,
      "Type": 0,
      "QuestRequired": false,
      "ItemName": "(MP)DrugLarge"
    },
    {
      "Chance": 1,
      "Gold": 0,
      "GroupedDrop": null,
      "Type": 0,
      "QuestRequired": false,
      "ItemName": "(MP)DrugLarge"
    },
    {
      "Chance": 1,
      "Gold": 0,
      "GroupedDrop": null,
      "Type": 0,
      "QuestRequired": false,
      "ItemName": "(MP)DrugLarge"
    },
    {
      "Chance": 2,
      "Gold": 0,
      "GroupedDrop": null,
      "Type": 0,
      "QuestRequired": false,
      "ItemName": "(HP)DrugLarge"
    },
    {
      "Chance": 1,
      "Gold": 0,
      "GroupedDrop": null,
      "Type": 0,
      "QuestRequired": false,
      "ItemName": "SunPotion(M)"
    },
    {
      "Chance": 1,
      "Gold": 0,
      "GroupedDrop": null,
      "Type": 0,
      "QuestRequired": false,
      "ItemName": "(HP)DrugLarge"
    },
    {
      "Chance": 2,
      "Gold": 0,
      "GroupedDrop": null,
      "Type": 0,
      "QuestRequired": false,
      "ItemName": "(MP)DrugLarge"
    },
    {
      "Chance": 2,
      "Gold": 0,
      "GroupedDrop": null,
      "Type": 0,
      "QuestRequired": false,
      "ItemName": "(MP)DrugLarge"
    },
    {
      "Chance": 2,
      "Gold": 0,
      "GroupedDrop": null,
      "Type": 0,
      "QuestRequired": false,
      "ItemName": "(MP)DrugLarge"
    },
    {
      "Chance": 1,
      "Gold": 0,
      "GroupedDrop": null,
      "Type": 0,
      "QuestRequired": false,
      "ItemName": "SunPotion(M)"
    },
    {
      "Chance": 1,
      "Gold": 0,
      "GroupedDrop": null,
      "Type": 0,
      "QuestRequired": false,
      "ItemName": "SunPotion(M)"
    },
    {
      "Chance": 1,
      "Gold": 0,
      "GroupedDrop": null,
      "Type": 0,
      "QuestRequired": false,
      "ItemName": "SunPotion(M)"
    },
    {
      "Chance": 2,
      "Gold": 0,
      "GroupedDrop": null,
      "Type": 0,
      "QuestRequired": false,
      "ItemName": "(HP)DrugLarge"
    },
    {
      "Chance": 1,
      "Gold": 0,
      "GroupedDrop": null,
      "Type": 0,
      "QuestRequired": false,
      "ItemName": "(HP)DrugLarge"
    },
    {
      "Chance": 5,
      "Gold": 0,
      "GroupedDrop": null,
      "Type": 0,
      "QuestRequired": false,
      "ItemName": "BenedictionOil"
    },
    {
      "Chance": 300,
      "Gold": 0,
      "GroupedDrop": null,
      "Type": 0,
      "QuestRequired": false,
      "ItemName": "MagicOrb"
    },
    {
      "Chance": 300,
      "Gold": 0,
      "GroupedDrop": null,
      "Type": 0,
      "QuestRequired": false,
      "ItemName": "BraveryOrb"
    },
    {
      "Chance": 300,
      "Gold": 0,
      "GroupedDrop": null,
      "Type": 0,
      "QuestRequired": false,
      "ItemName": "SoulOrb"
    },
    {
      "Chance": 300,
      "Gold": 0,
      "GroupedDrop": null,
      "Type": 0,
      "QuestRequired": false,
      "ItemName": "PoisonOrb"
    },
    {
      "Chance": 300,
      "Gold": 0,
      "GroupedDrop": null,
      "Type": 0,
      "QuestRequired": false,
      "ItemName": "EvilSlayerOrb"
    },
    {
      "Chance": 300,
      "Gold": 0,
      "GroupedDrop": null,
      "Type": 0,
      "QuestRequired": false,
      "ItemName": "DurabilityOrb"
    },
    {
      "Chance": 300,
      "Gold": 0,
      "GroupedDrop": null,
      "Type": 0,
      "QuestRequired": false,
      "ItemName": "ProtectionOrb"
    },
    {
      "Chance": 300,
      "Gold": 0,
      "GroupedDrop": null,
      "Type": 0,
      "QuestRequired": false,
      "ItemName": "FreezingOrb"
    },
    {
      "Chance": 300,
      "Gold": 0,
      "GroupedDrop": null,
      "Type": 0,
      "QuestRequired": false,
      "ItemName": "AgilityOrb"
    },
    {
      "Chance": 300,
      "Gold": 0,
      "GroupedDrop": null,
      "Type": 0,
      "QuestRequired": false,
      "ItemName": "AccuracyOrb"
    },
    {
      "Chance": 500,
      "Gold": 0,
      "GroupedDrop": null,
      "Type": 0,
      "QuestRequired": false,
      "ItemName": "DarkBody"
    },
    {
      "Chance": 200,
      "Gold": 0,
      "GroupedDrop": null,
      "Type": 0,
      "QuestRequired": false,
      "ItemName": "SummonHolyDeva"
    },
    {
      "Chance": 200,
      "Gold": 0,
      "GroupedDrop": null,
      "Type": 0,
      "QuestRequired": false,
      "ItemName": "Mirroring"
    },
    {
      "Chance": 200,
      "Gold": 0,
      "GroupedDrop": null,
      "Type": 0,
      "QuestRequired": false,
      "ItemName": "BladeAvalanche"
    },
    {
      "Chance": 200,
      "Gold": 0,
      "GroupedDrop": null,
      "Type": 0,
      "QuestRequired": false,
      "ItemName": "MPEater"
    },
    {
      "Chance": 500,
      "Gold": 0,
      "GroupedDrop": null,
      "Type": 0,
      "QuestRequired": false,
      "ItemName": "ProtectionField"
    },
    {
      "Chance": 500,
      "Gold": 0,
      "GroupedDrop": null,
      "Type": 0,
      "QuestRequired": false,
      "ItemName": "PoisonCloud"
    },
    {
      "Chance": 500,
      "Gold": 0,
      "GroupedDrop": null,
      "Type": 0,
      "QuestRequired": false,
      "ItemName": "Reincarnation"
    },
    {
      "Chance": 600,
      "Gold": 0,
      "GroupedDrop": null,
      "Type": 0,
      "QuestRequired": false,
      "ItemName": "EnergyShield"
    },
    {
      "Chance": 600,
      "Gold": 0,
      "GroupedDrop": null,
      "Type": 0,
      "QuestRequired": false,
      "ItemName": "FireBurst"
    },
    {
      "Chance": 400,
      "Gold": 0,
      "GroupedDrop": null,
      "Type": 0,
      "QuestRequired": false,
      "ItemName": "Rage"
    },
    {
      "Chance": 400,
      "Gold": 0,
      "GroupedDrop": null,
      "Type": 0,
      "QuestRequired": false,
      "ItemName": "ProtectionField"
    },
    {
      "Chance": 550,
      "Gold": 0,
      "GroupedDrop": null,
      "Type": 0,
      "QuestRequired": false,
      "ItemName": "Blizzard"
    },
    {
      "Chance": 500,
      "Gold": 0,
      "GroupedDrop": null,
      "Type": 0,
      "QuestRequired": false,
      "ItemName": "Rage"
    },
    {
      "Chance": 500,
      "Gold": 0,
      "GroupedDrop": null,
      "Type": 0,
      "QuestRequired": false,
      "ItemName": "MeteorStrike"
    },
    {
      "Chance": 1,
      "Gold": 18000,
      "GroupedDrop": null,
      "Type": 0,
      "QuestRequired": false,
      "ItemName": ""
    }
  ],
  "CanTame": false,
  "CanPush": false,
  "AutoRev": true,
  "Undead": false,
  "HasSpawnScript": false,
  "HasDieScript": false,
  "Stats": {
    "Values": {
      "MinAC": 35,
      "MaxAC": 35,
      "MinMAC": 50,
      "MaxMAC": 50,
      "MinDC": 70,
      "MaxDC": 100,
      "MinMC": 70,
      "MaxMC": 80,
      "Accuracy": 22,
      "Agility": 22,
      "HP": 15000
    },
    "Count": 15534
  },
  "GameName": "MinotaurKing"
}