{
  "Index": 51,
  "Name": "OmaFighter0",
  "Image": 17,
  "AI": 0,
  "Effect": 0,
  "ViewRange": 7,
  "CoolEye": 0,
  "Level": 22,
  "Light": 0,
  "AttackSpeed": 2000,
  "MoveSpeed": 1500,
  "Experience": 130,
  "DropPath": "",
  "Drops": [
    {
      "Chance": 12,
      "Gold": 0,
      "GroupedDrop": null,
      "Type": 0,
      "QuestRequired": false,
      "ItemName": "BoneBow"
    },
    {
      "Chance": 9,
      "Gold": 0,
      "GroupedDrop": null,
      "Type": 0,
      "QuestRequired": false,
      "ItemName": "Dagger"
    },
    {
      "Chance": 9,
      "Gold": 0,
      "GroupedDrop": null,
      "Type": 0,
      "QuestRequired": false,
      "ItemName": "EbonySword"
    },
    {
      "Chance": 9,
      "Gold": 0,
      "GroupedDrop": null,
      "Type": 0,
      "QuestRequired": false,
      "ItemName": "EbonyBow"
    },
    {
      "Chance": 10,
      "Gold": 0,
      "GroupedDrop": null,
      "Type": 0,
      "QuestRequired": false,
      "ItemName": "BronzeSword"
    },
    {
      "Chance": 10,
      "Gold": 0,
      "GroupedDrop": null,
      "Type": 0,
      "QuestRequired": false,
      "ItemName": "ShortBow"
    },
    {
      "Chance": 10,
      "Gold": 0,
      "GroupedDrop": null,
      "Type": 0,
      "QuestRequired": false,
      "ItemName": "SharpHoaSword"
    },
    {
      "Chance": 12,
      "Gold": 0,
      "GroupedDrop": null,
      "Type": 0,
      "QuestRequired": false,
      "ItemName": "IronSword"
    },
    {
      "Chance": 22,
      "Gold": 0,
      "GroupedDrop": null,
      "Type": 0,
      "QuestRequired": false,
      "ItemName": "ShortSword"
    },
    {
      "Chance": 7,
      "Gold": 0,
      "GroupedDrop": null,
      "Type": 0,
      "QuestRequired": false,
      "ItemName": "LightArmour(M)"
    },
    {
      "Chance": 7,
      "Gold": 0,
      "GroupedDrop": null,
      "Type": 0,
      "QuestRequired": false,
      "ItemName": "LightArmour(F)"
    },
    {
      "Chance": 7,
      "Gold": 0,
      "GroupedDrop": null,
      "Type": 0,
      "QuestRequired": false,
      "ItemName": "BronzeHelmet"
    },
    {
      "Chance": 11,
      "Gold": 0,
      "GroupedDrop": null,
      "Type": 0,
      "QuestRequired": false,
      "ItemName": "MagicHelmet"
    },
    {
      "Chance": 70,
      "Gold": 0,
      "GroupedDrop": null,
      "Type": 0,
      "QuestRequired": false,
      "ItemName": "AmberNecklace"
    },
    {
      "Chance": 16,
      "Gold": 0,
      "GroupedDrop": null,
      "Type": 0,
      "QuestRequired": false,
      "ItemName": "EbonyNecklace"
    },
    {
      "Chance": 70,
      "Gold": 0,
      "GroupedDrop": null,
      "Type": 0,
      "QuestRequired": false,
      "ItemName": "NagaNecklace"
    },
    {
      "Chance": 70,
      "Gold": 0,
      "GroupedDrop": null,
      "Type": 0,
      "QuestRequired": false,
      "ItemName": "PhoenixBead"
    },
    {
      "Chance": 16,
      "Gold": 0,
      "GroupedDrop": null,
      "Type": 0,
      "QuestRequired": false,
      "ItemName": "YellowNecklace"
    },
    {
      "Chance": 16,
      "Gold": 0,
      "GroupedDrop": null,
      "Type": 0,
      "QuestRequired": false,
      "ItemName": "BlackNecklace"
    },
    {
      "Chance": 8,
      "Gold": 0,
      "GroupedDrop": null,
      "Type": 0,
      "QuestRequired": false,
      "ItemName": "PrecisionNecklace"
    },
    {
      "Chance": 6,
      "Gold": 0,
      "GroupedDrop": null,
      "Type": 0,
      "QuestRequired": false,
      "ItemName": "GoldNecklace"
    },
    {
      "Chance": 8,
      "Gold": 0,
      "GroupedDrop": null,
      "Type": 0,
      "QuestRequired": false,
      "ItemName": "IronBracelet"
    },
    {
      "Chance": 30,
      "Gold": 0,
      "GroupedDrop": null,
      "Type": 0,
      "QuestRequired": false,
      "ItemName": "ThinBracelet"
    },
    {
      "Chance": 30,
      "Gold": 0,
      "GroupedDrop": null,
      "Type": 0,
      "QuestRequired": false,
      "ItemName": "LeatherGlove"
    },
    {
      "Chance": 40,
      "Gold": 0,
      "GroupedDrop": null,
      "Type": 0,
      "QuestRequired": false,
      "ItemName": "SteelBracelet"
    },
    {
      "Chance": 40,
      "Gold": 0,
      "GroupedDrop": null,
      "Type": 0,
      "QuestRequired": false,
      "ItemName": "SilverBracelet"
    },
    {
      "Chance": 40,
      "Gold": 0,
      "GroupedDrop": null,
      "Type": 0,
      "QuestRequired": false,
      "ItemName": "LargeBracelet"
    },
    {
      "Chance": 11,
      "Gold": 0,
      "GroupedDrop": null,
      "Type": 0,
      "QuestRequired": false,
      "ItemName": "GlassRing"
    },
    {
      "Chance": 6,
      "Gold": 0,
      "GroupedDrop": null,
      "Type": 0,
      "QuestRequired": false,
      "ItemName": "CopperRing"
    },
    {
      "Chance": 11,
      "Gold": 0,
      "GroupedDrop": null,
      "Type": 0,
      "QuestRequired": false,
      "ItemName": "HornRing"
    },
    {
      "Chance": 11,
      "Gold": 0,
      "GroupedDrop": null,
      "Type": 0,
      "QuestRequired": false,
      "ItemName": "HexagonalRing"
    },
    {
      "Chance": 20,
      "Gold": 0,
      "GroupedDrop": null,
      "Type": 0,
      "QuestRequired": false,
      "ItemName": "BlueRing"
    },
    {
      "Chance": 4,
      "Gold": 0,
      "GroupedDrop": null,
      "Type": 0,
      "QuestRequired": false,
      "ItemName": "(HP)DrugMedium"
    },
    {
      "Chance": 60,
      "Gold": 0,
      "GroupedDrop": null,
      "Type": 0,
      "QuestRequired": false,
      "ItemName": "SunPotion"
    },
    {
      "Chance": 4,
      "Gold": 0,
      "GroupedDrop": null,
      "Type": 0,
      "QuestRequired": false,
      "ItemName": "(MP)DrugMedium"
    },
    {
      "Chance": 1,
      "Gold": 2000,
      "GroupedDrop": null,
      "Type": 0,
      "QuestRequired": false,
      "ItemName": ""
    }
  ],
  "CanTame": true,
  "CanPush": true,
  "AutoRev": true,
  "Undead": false,
  "HasSpawnScript": false,
  "HasDieScript": false,
  "Stats": {
    "Values": {
      "MinAC": 3,
      "MaxAC": 3,
      "MinMAC": 1,
      "MaxMAC": 1,
      "MinDC": 7,
      "MaxDC": 12,
      "Accuracy": 10,
      "Agility": 15,
      "HP": 100
    },
    "Count": 152
  },
  "GameName": "OmaFighter"
}