{
  "Index": 303,
  "Name": "SpiderBat",
  "Image": 52,
  "AI": 7,
  "Effect": 0,
  "ViewRange": 7,
  "CoolEye": 0,
  "Level": 52,
  "Light": 0,
  "AttackSpeed": 2000,
  "MoveSpeed": 500,
  "Experience": 540,
  "DropPath": "",
  "Drops": [
    {
      "Chance": 1000000,
      "Gold": 0,
      "GroupedDrop": null,
      "Type": 0,
      "QuestRequired": false,
      "ItemName": "ParalysisRing"
    },
    {
      "Chance": 10,
      "Gold": 0,
      "GroupedDrop": null,
      "Type": 0,
      "QuestRequired": false,
      "ItemName": "(HP)DrugMedium"
    },
    {
      "Chance": 10,
      "Gold": 0,
      "GroupedDrop": null,
      "Type": 0,
      "QuestRequired": false,
      "ItemName": "(MP)DrugMedium"
    },
    {
      "Chance": 20,
      "Gold": 0,
      "GroupedDrop": null,
      "Type": 0,
      "QuestRequired": false,
      "ItemName": "(HP)DrugLarge"
    },
    {
      "Chance": 20,
      "Gold": 0,
      "GroupedDrop": null,
      "Type": 0,
      "QuestRequired": false,
      "ItemName": "(MP)DrugLarge"
    },
    {
      "Chance": 40,
      "Gold": 0,
      "GroupedDrop": null,
      "Type": 0,
      "QuestRequired": false,
      "ItemName": "TownTeleport"
    },
    {
      "Chance": 6,
      "Gold": 0,
      "GroupedDrop": null,
      "Type": 0,
      "QuestRequired": true,
      "ItemName": "BatPoison"
    },
    {
      "Chance": 5,
      "Gold": 500,
      "GroupedDrop": null,
      "Type": 0,
      "QuestRequired": false,
      "ItemName": ""
    }
  ],
  "CanTame": true,
  "CanPush": true,
  "AutoRev": true,
  "Undead": false,
  "HasSpawnScript": false,
  "HasDieScript": false,
  "Stats": {
    "Values": {
      "MinAC": 1,
      "MaxAC": 3,
      "MinMAC": 2,
      "MaxMAC": 9,
      "MinDC": 10,
      "MaxDC": 35,
      "Accuracy": 15,
      "Agility": 16,
      "HP": 300
    },
    "Count": 391
  },
  "GameName": "SpiderBat"
}